linearlr.py
linearlr-0.0.1.dist-info/LICENSE.txt
linearlr-0.0.1.dist-info/METADATA
linearlr-0.0.1.dist-info/WHEEL
linearlr-0.0.1.dist-info/top_level.txt
linearlr-0.0.1.dist-info/RECORD
